language_processing_tool/__init__.py
language_processing_tool/process_pdfs.py
language_processing_tool-0.2.5.dist-info/LICENSE
language_processing_tool-0.2.5.dist-info/METADATA
language_processing_tool-0.2.5.dist-info/WHEEL
language_processing_tool-0.2.5.dist-info/entry_points.txt
language_processing_tool-0.2.5.dist-info/top_level.txt
language_processing_tool-0.2.5.dist-info/RECORD
