Metadata-Version: 2.1
Name: language-processing-tool
Version: 0.2.5
Summary: A PDF language detection and OCR tool
Home-page: https://github.com/Harish-nika/language-processing-tool
Author: Harish Kumar S
Author-email: harishkumar56278@gmail.com
License: UNKNOWN
Platform: UNKNOWN
Classifier: Programming Language :: Python :: 3
Classifier: License :: OSI Approved :: MIT License
Classifier: Operating System :: OS Independent
Requires-Python: >=3.6
License-File: LICENSE
Requires-Dist: Pillow
Requires-Dist: PyMuPDF
Requires-Dist: argparse
Requires-Dist: icecream
Requires-Dist: langdetect
Requires-Dist: pandas
Requires-Dist: pytesseract
